LICENSE
README.md
setup.cfg
setup.py
dipple/__init__.py
dipple/activation.py
dipple/compute_cost.py
dipple/debug_util.py
dipple/import_dataset.py
dipple/initializer.py
dipple/interpret.py
dipple/load.py
dipple/losses.py
dipple/metrics.py
dipple/mlp.py
dipple/mlp_component.py
dipple/optimizer.py
dipple/regularization.py
dipple/update_params.py
dipple.egg-info/PKG-INFO
dipple.egg-info/SOURCES.txt
dipple.egg-info/dependency_links.txt
dipple.egg-info/requires.txt
dipple.egg-info/top_level.txt
dipple/utils/__init__.py
dipple/utils/py_util.py