Metadata-Version: 2.1
Name: dipple
Version: 1.0.2
Summary: All of the neural network architecture, with a simple implementation
Home-page: https://github.com/wallik2/dipple
Author: Saran Pannasuriyaporn
Author-email: runpan4work@gmail.com
License: MIT
Platform: UNKNOWN
Classifier: Programming Language :: Python :: 3
Classifier: License :: OSI Approved :: MIT License
Classifier: Operating System :: OS Independent
Requires-Python: >=3.7
Provides-Extra: dev
